playmolecule/__init__.py
playmolecule/_test_funcs.py
playmolecule/_version.py
playmolecule/config.ini
playmolecule/config.py
playmolecule/datacenter.py
playmolecule/devutils.py
playmolecule/job.py
playmolecule/jsonlogger.py
playmolecule/local.py
playmolecule/logging.ini
playmolecule/playqueue.py
playmolecule/session.py
playmolecule/utils.py
playmolecule-1.9.2.dist-info/LICENSE.md
playmolecule-1.9.2.dist-info/METADATA
playmolecule-1.9.2.dist-info/WHEEL
playmolecule-1.9.2.dist-info/top_level.txt
playmolecule-1.9.2.dist-info/RECORD
