Metadata-Version: 2.1
Name: playmolecule
Version: 1.9.2
Summary: PlayMolecule python API
Author-email: Acellera <info@acellera.com>
Project-URL: Homepage, https://github.com/Acellera/playmolecule-python-api
Project-URL: Bug Tracker, https://github.com/Acellera/playmolecule-python-api/issues
Classifier: Programming Language :: Python :: 3
Classifier: Operating System :: POSIX :: Linux
Requires-Python: >=3.8
License-File: LICENSE.md
Requires-Dist: protocolinterface
Requires-Dist: requests
Requires-Dist: PyYaml
Requires-Dist: python-dateutil
Requires-Dist: func2argparse
